{
    "CarDrive": {
        "checkpoints": [
            {
                "steps": 499956,
                "file_path": "results\\CarDrive5\\CarDrive\\CarDrive-499956.onnx",
                "reward": -0.5617426835000515,
                "creation_time": 1610934853.5394707
            },
            {
                "steps": 500020,
                "file_path": "results\\CarDrive5\\CarDrive\\CarDrive-500020.onnx",
                "reward": -0.5617426835000515,
                "creation_time": 1610934853.5816305
            }
        ],
        "final_checkpoint": {
            "steps": 500020,
            "file_path": "results\\CarDrive5\\CarDrive.onnx",
            "reward": -0.5617426835000515,
            "creation_time": 1610934853.5816305
        }
    },
    "metadata": {
        "stats_format_version": "0.2.0",
        "mlagents_version": "0.23.0",
        "torch_version": "1.7.0+cu110",
        "tensorflow_version": -1
    }
}